{"version":1,"resource":"vscode-userdata:/c%3A/Users/bryan/AppData/Roaming/Code%20-%20Insiders/User/settings.json","entries":[{"id":"N419.json","timestamp":1651716622391},{"id":"hIVy.json","timestamp":1651716959587},{"id":"4dRZ.json","timestamp":1652654377214},{"id":"UMto.json","timestamp":1652668543337},{"id":"qlOr.json","timestamp":1652669986867},{"id":"RBRi.json","timestamp":1652670030776},{"id":"Y43W.json","timestamp":1652670047957},{"id":"Z3EF.json","timestamp":1653243852510},{"id":"nGDV.json","timestamp":1653243882633},{"id":"VkTY.json","timestamp":1655013090208},{"id":"ZSTn.json","timestamp":1655041978906}]}