{
  "version": 1,
  "resource": "file:///Users/BGuner/BGOONZ_BLOG_2.0/docs/content/MDN/glossary/placeholder_namesindex.md",
  "entries": [
    {
      "id": "tTAQ.md",
      "source": "searchReplace.source",
      "timestamp": 1649259608877
    },
    {
      "id": "iTFQ.md",
      "source": "searchReplace.source",
      "timestamp": 1649259651699
    },
    {
      "id": "chDt.md",
      "source": "searchReplace.source",
      "timestamp": 1649259686442
    },
    {
      "id": "pqOm.md",
      "source": "searchReplace.source",
      "timestamp": 1649259876428
    },
    {
      "id": "f5dL.md",
      "source": "searchReplace.source",
      "timestamp": 1649259939100
    },
    {
      "id": "BY9M.md",
      "source": "searchReplace.source",
      "timestamp": 1649259954253
    },
    {
      "id": "YKdO.md",
      "source": "searchReplace.source",
      "timestamp": 1649260020137
    },
    {
      "id": "LMBB.md",
      "source": "searchReplace.source",
      "timestamp": 1649260065752
    },
    {
      "id": "dk5r.md",
      "source": "searchReplace.source",
      "timestamp": 1649260089113
    },
    {
      "id": "wGc9.md",
      "source": "searchReplace.source",
      "timestamp": 1649260160870
    },
    {
      "id": "0X6C.md",
      "source": "searchReplace.source",
      "timestamp": 1649260208840
    },
    {
      "id": "6j3m.md",
      "source": "searchReplace.source",
      "timestamp": 1649260348255
    },
    {
      "id": "DPMM.md",
      "source": "searchReplace.source",
      "timestamp": 1649260699263
    },
    { "id": "h2vU.md", "timestamp": 1649260794794 },
    {
      "id": "CDWU.md",
      "source": "searchReplace.source",
      "timestamp": 1649262171435
    }
  ]
}
